<persistence xmlns="http://xmlns.jcp.org/xml/ns/persistence"
             xmlns:xsi="http://www.w3.org/2001/XMLSchema-instance"
             xsi:schemaLocation="http://xmlns.jcp.org/xml/ns/persistence
             http://xmlns.jcp.org/xml/ns/persistence/persistence_2_2.xsd"
             version="2.2">

    <persistence-unit name="virtualStorePU" transaction-type="RESOURCE_LOCAL">
        <provider>org.eclipse.persistence.jpa.PersistenceProvider</provider>
        <class>model.Avaliacao</class>
        <class>model.Categoria</class>
        <class>model.Cliente</class>
        <class>model.Fornecedor</class>
        <class>model.Pagamento</class>
        <class>model.Pedido</class>
        <class>model.Produto</class>
        <exclude-unlisted-classes>false</exclude-unlisted-classes>
        <properties>
            <property name="jakarta.persistence.jdbc.driver" value="com.mysql.cj.jdbc.Driver"/>
            <property name="jakarta.persistence.jdbc.url" value="jdbc:mysql://localhost:3306/virtual_store"/>
            <property name="jakarta.persistence.jdbc.user" value="root"/>
            <property name="jakarta.persistence.jdbc.password" value=""/>

            <!-- Configurações para criação automática de tabelas -->
            <!-- update: cria tabelas automaticamente se não existirem, atualiza se existirem (não apaga dados existentes) -->
            <property name="jakarta.persistence.schema-generation.database.action" value="update"/>
            <property name="jakarta.persistence.schema-generation.create-source" value="metadata"/>
            <property name="jakarta.persistence.schema-generation.scripts.action" value="none"/>
            <!-- Configurações do EclipseLink para criação de tabelas -->
            <property name="eclipselink.ddl-generation" value="create-or-extend-tables"/>
            <property name="eclipselink.ddl-generation.output-mode" value="database"/>
            <property name="eclipselink.logging.level" value="INFO"/>
            <property name="eclipselink.logging.parameters" value="false"/>
        </properties>
    </persistence-unit>
</persistence>